dccmd/__init__.py
dccmd/main/__init__.py
dccmd/main/auth/__init__.py
dccmd/main/auth/client.py
dccmd/main/auth/credentials.py
dccmd/main/auth/util.py
dccmd/main/crypto/__init__.py
dccmd/main/crypto/keys.py
dccmd/main/crypto/util.py
dccmd/main/download/__init__.py
dccmd/main/models/__init__.py
dccmd/main/models/errors.py
dccmd/main/rooms/__init__.py
dccmd/main/rooms/models.py
dccmd/main/rooms/permissions.py
dccmd/main/rooms/print.py
dccmd/main/upload/__init__.py
dccmd/main/users/__init__.py
dccmd/main/users/manage.py
dccmd/main/users/print.py
dccmd/main/util/__init__.py
dccmd-0.5.0.dist-info/LICENSE
dccmd-0.5.0.dist-info/METADATA
dccmd-0.5.0.dist-info/WHEEL
dccmd-0.5.0.dist-info/entry_points.txt
dccmd-0.5.0.dist-info/RECORD
