Metadata-Version: 2.1
Name: dccmd
Version: 0.5.0
Summary: DRACOON Commander - CLI client for DRACOON Cloud (dracoon.com)
License: Apache-2.0
Author: Octavio Simone
Author-email: 70800577+unbekanntes-pferd@users.noreply.github.com
Requires-Python: >=3.10,<4.0
Classifier: License :: OSI Approved :: Apache Software License
Classifier: Programming Language :: Python :: 3
Classifier: Programming Language :: Python :: 3.10
Classifier: Programming Language :: Python :: 3.11
Classifier: Programming Language :: Python :: 3.12
Requires-Dist: SecretStorage (>=3.3.1,<4.0.0)
Requires-Dist: appdirs (>=1.4.4,<2.0.0)
Requires-Dist: dracoon (>=1.12.2,<2.0.0)
Requires-Dist: keyring (>=23.6.0,<24.0.0)
Requires-Dist: tqdm (>=4.65.0,<5.0.0)
Requires-Dist: typer (>=0.4.0,<0.5.0)
